Code/BalaBarController.sv
module BalaBArController (
    input clk,                          // Clock 
    input rst,                        // signal for reset
    input [4:0] buttons_ex,       // request from out
    input [4:0] buttons_in,       // request from in
    input [4:0] floor_cur,          // Current floor
    output reg direction,               // Move Direction signal : 1 ->  up, 0 -> down
    output reg motor                    // Motor movement : 1 -> motor, 0 -> stop 
);

    // local variable
    reg [4:0] requests;
    integer i;
    integer target;
    bit [2:0] queue [$:4]; 
    bit new_target;
    localparam STOP = 2'b00;
    localparam UP_going = 2'b11;
    localparam DOWN_going = 2'b10;

    // initial
    initial begin
        {motor, direction} = STOP;
        requests = {5{1'b0}};
    end

    function automatic void clear();
        int val;
        while (queue.size() != 0)
            val = queue.pop_front();
    endfunction

    // update requests
    always @(negedge clk or posedge rst) begin
        if (rst) begin
            new_target <= 1'b1;
            requests <= {5{1'b0}};
        end 
        else
            requests <= buttons_in | requests | buttons_ex;
    end

    // updating destination
    always @(posedge rst) begin
        if (rst)
            target = floor_cur;
    end


    // always for the control logic
    always @(negedge clk or posedge rst) begin
        if (rst)
            {motor, direction} <= STOP;
        else begin
            case ({motor, direction})
                STOP: begin
                    if (requests != {5{1'b0}}) begin
                        if (queue.size() > 0 && new_target)begin
                            target = queue.pop_front();
                            new_target = 0;
                        end
                        if (target > floor_cur)
                            {motor, direction} <= UP_going;
                        else if (target < floor_cur)
                            {motor, direction} <= DOWN_going;
                    end
                    if (target == floor_cur) begin
                            requests[floor_cur] <= 1'b0;
                            new_target = 1;
                        end
                end

                DOWN_going: begin
                    if (0 == floor_cur) begin
                        {motor, direction} <= STOP;
                    end
                    else begin
                        if (requests[floor_cur] == 1'b1) begin
                            {motor, direction} <= STOP;
                            requests[floor_cur] <= 1'b0;
                        end
                        if (target == floor_cur) begin
                            new_target = 1;
                            {motor, direction} = STOP;
                        end
                    end
                end

                UP_going: begin
                    if (5 == floor_cur) begin
                        {motor, direction} <= STOP;
                    end
                    else begin
                        if (requests[floor_cur] == 1'b1) begin
                            {motor, direction} <= STOP;
                            requests[floor_cur] <= 1'b0;
                        end
                        if (target == floor_cur) begin
                            new_target = 1;
                            {motor, direction} = STOP;
                        end
                    end 
                end
            endcase
        end
    end


    // always for the request queue
    always @(negedge clk or posedge rst) begin
        if (rst) 
            clear();

        else begin
            for (i = 0; i < 5 ; i= i+1) begin
                if (buttons_in[i] | buttons_ex[i] == 1'b1) begin
                    case ({motor, direction})
                        STOP: begin
                            if (target > floor_cur) begin
                                if (i < floor_cur)
                                    queue.push_back(i);
                                else if (i > target)
                                    queue.push_back(i);
                            end
                            else if (target < floor_cur) begin
                                if (i > floor_cur)
                                    queue.push_back(i);
                                else if (i < target)
                                    queue.push_back(i);
                            end
                            else
                                queue.push_back(i);
                        end

                        DOWN_going: begin
                            if(i < target || i > floor_cur)
                                queue.push_back(i);
                        end

                        UP_going: begin
                            if(i > target || floor_cur > i)
                                queue.push_back(i);
                        end

                    endcase
                end
            end
        end
    end

endmodule

Code/BalaBar.sv
module BalaBar (
    input clk,                                  // Clock
    input rst,                                // signal for reset
    input [1:0] state,                          // state of BalaBar
    output reg [4:0] floor_cur,             // Current floor
    output reg [1:0] floor_state [4:0]      //  floor states 
);

    // local variable
    integer i;
    localparam STOP = 2'b00;
    localparam UP_going = 2'b11;
    localparam DOWN_going = 2'b10;

    // initial
    initial begin
        floor_cur = {5{1'b0}};
        for( i = 0; i < 5; i=i+1)
            floor_state[i] = 2'b00;
    end

    // update states
    always @(posedge clk or posedge rst) begin
        for( i = 0; i < 5; i=i+1)
            floor_state[i] = 2'b00;

        if (rst) begin
            floor_cur = {5{1'b0}};
        end else begin
            case (state)
                STOP: begin
                    floor_state[floor_cur] = 2'b11;
                    #100;
                end

                DOWN_going: begin
                    if (floor_cur > 0) begin
                        floor_state[floor_cur] = 2'b01;
                        floor_cur = floor_cur - 1;
                        floor_state[floor_cur] = 2'b10;
                    end
                    #10;
                end

                UP_going: begin
                    if (floor_cur < 5) begin
                        floor_state[floor_cur] = 2'b01;
                        floor_cur = floor_cur + 1;
                        floor_state[floor_cur] = 2'b10;
                    end
                    #10;
                end

            endcase
        end
    end
endmodule

Code/TESTBENCH.sv
module TESTBENCH;

    // variable
    reg clk;
    reg rst;
    reg [4:0] buttons_in;
    reg [4:0] buttons_ex;
    wire motor;
    wire direction;
    wire [4:0] floor_cur;
    wire [1:0] floor_state [0:4];

    // instance
    BalaBar balaBar (
        .clk(clk),
        .rst(rst),
        .state({motor, direction}),
        .floor_state(floor_state),
        .floor_cur(floor_cur)
    );

    BalaBArController controller (
        .clk(clk),
        .rst(rst),
        .floor_cur(floor_cur),
        .buttons_in(buttons_in),
        .buttons_ex(buttons_ex),
        .direction(direction),
        .motor(motor)
    );

    always #5 clk = ~clk; // clock

    initial begin
        clk = 0;
        rst = 1;
        buttons_in = 0;
        buttons_ex = 0;
        
        #10 rst = 0;                      // t = 10
        buttons_ex[0] = 1'b1;
        #11 buttons_ex[0] = 1'b0;     // t = 20
        #10 buttons_in[2] = 1'b1;     // t = 30     
        #10 buttons_in[2] = 1'b0;     // t = 40
        #100
        buttons_ex[1] = 1'b1;         // t = 140
        #10 buttons_ex[1] = 1'b0;     // t = 150
        #10 buttons_ex[3] = 1'b1;     // t = 160
        #10 buttons_ex[3] = 1'b0;     // t = 170
        #10 buttons_ex[0] = 1'b1;     // t = 180
        #10 buttons_ex[0] = 1'b0;     // t = 190

        #60 buttons_in[2] = 1'b1;     // t = 250
        #10 buttons_in[2] = 1'b0;     // t = 260

        #210 buttons_in[0] = 1'b1;    // t = 470
        #10 buttons_in[0] = 1'b0;     // t = 480

        #130 buttons_in[4] = 1'b1;    // t = 610
        #10 buttons_in[4] = 1'b0;     // t = 620
        
        #20 buttons_ex[1] = 1'b1;     // t = 640
        #10 buttons_ex[1] = 1'b0;     // t = 650
        #1000;
        $stop();
    end

    initial begin
    
    $dumpfile("BalaBar.vcd");
    $dumpvars;
    end

    reg [1:0] pre [4:0];
    
    always @(posedge clk) begin
        if (floor_state !== pre) begin
            $display("at %4d moment", $time, " Floor state have change:\n this moment is :  %p", floor_state);
        end
        pre <= floor_state;
    end

endmodule

Code/BalaBar.vcd
$date
	Sat Jun 29 00:38:10 2024
$end
$version
	ModelSim Version 2020.1
$end
$timescale
	1ps
$end

$scope module TESTBENCH $end
$var reg 1 ! clk $end
$var reg 1 " rst $end
$var reg 5 # buttons_in [4:0] $end
$var reg 5 $ buttons_ex [4:0] $end
$var wire 1 % motor $end
$var wire 1 & direction $end
$var wire 1 ' floor_cur [4] $end
$var wire 1 ( floor_cur [3] $end
$var wire 1 ) floor_cur [2] $end
$var wire 1 * floor_cur [1] $end
$var wire 1 + floor_cur [0] $end
$var wire 1 , floor_state [0] $end
$var wire 1 - floor_state [1] $end
$var wire 1 . floor_state [2] $end
$var wire 1 / floor_state [3] $end
$var wire 1 0 floor_state [4] $end
$var wire 1 1 floor_state [5] $end
$var wire 1 2 floor_state [6] $end
$var wire 1 3 floor_state [7] $end
$var wire 1 4 floor_state [8] $end
$var wire 1 5 floor_state [9] $end

$scope module balaBar $end
$var parameter 2 6 STOP $end
$var parameter 2 7 UP_going $end
$var parameter 2 8 DOWN_going $end
$var wire 1 9 clk $end
$var wire 1 : rst $end
$var wire 1 % state [1] $end
$var wire 1 & state [0] $end
$var reg 5 ; floor_cur [4:0] $end
$var integer 32 < i $end
$upscope $end

$scope module controller $end
$var parameter 2 = STOP $end
$var parameter 2 > UP_going $end
$var parameter 2 ? DOWN_going $end
$var wire 1 @ clk $end
$var wire 1 A rst $end
$var wire 1 B buttons_ex [4] $end
$var wire 1 C buttons_ex [3] $end
$var wire 1 D buttons_ex [2] $end
$var wire 1 E buttons_ex [1] $end
$var wire 1 F buttons_ex [0] $end
$var wire 1 G buttons_in [4] $end
$var wire 1 H buttons_in [3] $end
$var wire 1 I buttons_in [2] $end
$var wire 1 J buttons_in [1] $end
$var wire 1 K buttons_in [0] $end
$var wire 1 ' floor_cur [4] $end
$var wire 1 ( floor_cur [3] $end
$var wire 1 ) floor_cur [2] $end
$var wire 1 * floor_cur [1] $end
$var wire 1 + floor_cur [0] $end
$var reg 1 L direction $end
$var reg 1 M motor $end
$var reg 5 N requests [4:0] $end
$var integer 32 O i $end
$var integer 32 P target $end
$var reg 1 Q new_target $end

$scope function clear $end
$upscope $end
$upscope $end
$upscope $end

$scope begin std $end
$upscope $end
$enddefinitions $end
#0
$dumpvars
0!
1"
b0 #
b0 $
b0 ;
0L
0M
b0 N
1Q
b0 6
b11 7
b10 8
b0 =
b11 >
b10 ?
b101 <
bx O
b0 P
0%
0&
0+
0*
0)
0(
0'
0,
0-
0.
0/
00
01
02
03
04
05
09
1:
0@
1A
0K
0J
0I
0H
0G
0F
0E
0D
0C
0B
$end
#5
1!
1@
19
b0 <
b1 <
b10 <
b11 <
b100 <
b101 <
#10
0"
0!
0A
0:
0@
09
b0 O
b1 O
b10 O
b11 O
b100 O
b101 O
#15
1!
1@
19
b0 <
b1 <
b10 <
b11 <
b100 <
b101 <
14
15
#20
b10000 #
0!
1G
0@
09
b0 O
b1 O
b10 O
b11 O
b100 O
b101 O
b10000 N
#25
1!
1@
19
#30
b0 #
0!
0G
0@
09
b100 P
0Q
b0 O
b1 O
b10 O
b11 O
b100 O
b101 O
1L
1M
1&
1%
#35
1!
1@
19
#40
0!
0@
09
b0 O
b1 O
b10 O
b11 O
b100 O
b101 O
#45
1!
1@
19
#50
0!
0@
09
b0 O
b1 O
b10 O
b11 O
b100 O
b101 O
#55
1!
1@
19
#60
0!
0@
09
b0 O
b1 O
b10 O
b11 O
b100 O
b101 O
#65
1!
1@
19
#70
0!
0@
09
b0 O
b1 O
b10 O
b11 O
b100 O
b101 O
#75
1!
1@
19
#80
0!
0@
09
b0 O
b1 O
b10 O
b11 O
b100 O
b101 O
#85
1!
1@
19
#90
0!
0@
09
b0 O
b1 O
b10 O
b11 O
b100 O
b101 O
#95
1!
1@
19
#100
0!
0@
09
b0 O
b1 O
b10 O
b11 O
b100 O
b101 O
#105
1!
1@
19
#110
0!
0@
09
b0 O
b1 O
b10 O
b11 O
b100 O
b101 O
#115
1!
1@
19
b0 <
b1 <
b10 <
b11 <
b100 <
b101 <
b1 ;
1+
13
05
#120
0!
0@
09
b0 O
b1 O
b10 O
b11 O
b100 O
b101 O
#125
1!
1@
19
b0 <
b1 <
b10 <
b11 <
b100 <
b101 <
b10 ;
0+
1*
11
12
03
04
#130
0!
0@
09
b0 O
b1 O
b10 O
b11 O
b100 O
b101 O
#135
1!
1@
19
b0 <
b1 <
b10 <
b11 <
b100 <
b101 <
b11 ;
1+
1/
10
01
02
#140
b1 $
0!
1F
0@
09
b0 O
b1 O
b10 O
b11 O
b100 O
b101 O
b10001 N
#145
1!
1@
19
b0 <
b1 <
b10 <
b11 <
b100 <
b101 <
b100 ;
0+
0*
1)
1-
1.
0/
00
#150
b0 $
0!
0F
0@
09
1Q
0L
0M
b0 O
b1 O
b10 O
b11 O
b100 O
b101 O
0&
0%
b1 N
#155
1!
1@
19
b0 <
b1 <
b10 <
b11 <
b100 <
b101 <
1,
0.
#160
b10 $
0!
1E
0@
09
b0 P
0Q
b0 O
b1 O
b10 O
b11 O
b100 O
b101 O
b11 N
1M
1%
#165
1!
1@
19
#170
b0 $
0!
0E
0@
09
b0 O
b1 O
b10 O
b11 O
b100 O
b101 O
#175
1!
1@
19
#180
0!
0@
09
b0 O
b1 O
b10 O
b11 O
b100 O
b101 O
#185
1!
1@
19
#190
0!
0@
09
b0 O
b1 O
b10 O
b11 O
b100 O
b101 O
#195
1!
1@
19
#200
0!
0@
09
b0 O
b1 O
b10 O
b11 O
b100 O
b101 O
#205
1!
1@
19
#210
0!
0@
09
b0 O
b1 O
b10 O
b11 O
b100 O
b101 O
#215
1!
1@
19
#220
0!
0@
09
b0 O
b1 O
b10 O
b11 O
b100 O
b101 O
#225
1!
1@
19
#230
b1000 #
0!
1H
0@
09
b0 O
b1 O
b10 O
b11 O
b100 O
b101 O
b1011 N
#235
1!
1@
19
#240
b0 #
0!
0H
0@
09
b0 O
b1 O
b10 O
b11 O
b100 O
b101 O
#245
1!
1@
19
#250
0!
0@
09
b0 O
b1 O
b10 O
b11 O
b100 O
b101 O
#255
1!
1@
19
b0 <
b1 <
b10 <
b11 <
b100 <
b101 <
b11 ;
1+
1*
0)
0-
1/
#260
0!
0@
09
b0 O
b1 O
b10 O
b11 O
b100 O
b101 O
0M
b11 N
0%
#265
1!
1@
19
b0 <
b1 <
b10 <
b11 <
b100 <
b101 <
0,
1.
#270
0!
0@
09
b0 O
b1 O
b10 O
b11 O
b100 O
b101 O
1M
1%
#275
1!
1@
19
#280
0!
0@
09
b0 O
b1 O
b10 O
b11 O
b100 O
b101 O
#285
1!
1@
19
#290
0!
0@
09
b0 O
b1 O
b10 O
b11 O
b100 O
b101 O
#295
1!
1@
19
#300
0!
0@
09
b0 O
b1 O
b10 O
b11 O
b100 O
b101 O
#305
1!
1@
19
#310
0!
0@
09
b0 O
b1 O
b10 O
b11 O
b100 O
b101 O
#315
1!
1@
19
#320
0!
0@
09
b0 O
b1 O
b10 O
b11 O
b100 O
b101 O
#325
1!
1@
19
#330
0!
0@
09
b0 O
b1 O
b10 O
b11 O
b100 O
b101 O
#335
1!
1@
19
#340
0!
0@
09
b0 O
b1 O
b10 O
b11 O
b100 O
b101 O
#345
1!
1@
19
#350
0!
0@
09
b0 O
b1 O
b10 O
b11 O
b100 O
b101 O
#355
1!
1@
19
#360
0!
0@
09
b0 O
b1 O
b10 O
b11 O
b100 O
b101 O
#365
1!
1@
19
b0 <
b1 <
b10 <
b11 <
b100 <
b101 <
b10 ;
0+
0/
11
#370
0!
0@
09
b0 O
b1 O
b10 O
b11 O
b100 O
b101 O
#375
1!
1@
19
b0 <
b1 <
b10 <
b11 <
b100 <
b101 <
b1 ;
1+
0*
0.
10
01
13
#380
0!
0@
09
b0 O
b1 O
b10 O
b11 O
b100 O
b101 O
0M
b1 N
0%
#385
1!
1@
19
b0 <
b1 <
b10 <
b11 <
b100 <
b101 <
00
12
#390
0!
0@
09
b0 O
b1 O
b10 O
b11 O
b100 O
b101 O
1M
1%
#395
1!
1@
19
#400
0!
0@
09
b0 O
b1 O
b10 O
b11 O
b100 O
b101 O
#405
1!
1@
19
#410
0!
0@
09
b0 O
b1 O
b10 O
b11 O
b100 O
b101 O
#415
1!
1@
19
#420
0!
0@
09
b0 O
b1 O
b10 O
b11 O
b100 O
b101 O
#425
1!
1@
19
#430
0!
0@
09
b0 O
b1 O
b10 O
b11 O
b100 O
b101 O
#435
1!
1@
19
#440
0!
0@
09
b0 O
b1 O
b10 O
b11 O
b100 O
b101 O
#445
1!
1@
19
#450
0!
0@
09
b0 O
b1 O
b10 O
b11 O
b100 O
b101 O
#455
1!
1@
19
#460
0!
0@
09
b0 O
b1 O
b10 O
b11 O
b100 O
b101 O
#465
1!
1@
19
#470
0!
0@
09
b0 O
b1 O
b10 O
b11 O
b100 O
b101 O
#475
1!
1@
19
#480
0!
0@
09
b0 O
b1 O
b10 O
b11 O
b100 O
b101 O
#485
1!
1@
19
b0 <
b1 <
b10 <
b11 <
b100 <
b101 <
b0 ;
0+
03
15
#490
0!
0@
09
b0 O
b1 O
b10 O
b11 O
b100 O
b101 O
0M
0%
#495
1!
1@
19
b0 <
b1 <
b10 <
b11 <
b100 <
b101 <
02
14
#500
0!
0@
09
1Q
b0 O
b1 O
b10 O
b11 O
b100 O
b101 O
b0 N
#505
1!
1@
19
#510
0!
0@
09
b0 O
b1 O
b10 O
b11 O
b100 O
b101 O
#515
1!
1@
19
#520
0!
0@
09
b0 O
b1 O
b10 O
b11 O
b100 O
b101 O
#525
1!
1@
19
#530
0!
0@
09
b0 O
b1 O
b10 O
b11 O
b100 O
b101 O
#535
1!
1@
19
#540
0!
0@
09
b0 O
b1 O
b10 O
b11 O
b100 O
b101 O
#545
1!
1@
19
#550
b100 #
0!
1I
0@
09
b0 O
b1 O
b10 O
b11 O
b100 O
b101 O
b100 N
#555
1!
1@
19
#560
b0 #
0!
0I
0@
09
b10 P
0Q
b0 O
b1 O
b10 O
b11 O
b100 O
b101 O
1L
1M
1&
1%
#565
1!
1@
19
#570
0!
0@
09
b0 O
b1 O
b10 O
b11 O
b100 O
b101 O
#575
1!
1@
19
#580
0!
0@
09
b0 O
b1 O
b10 O
b11 O
b100 O
b101 O
#585
1!
1@
19
#590
0!
0@
09
b0 O
b1 O
b10 O
b11 O
b100 O
b101 O
#595
1!
1@
19
b0 <
b1 <
b10 <
b11 <
b100 <
b101 <
b1 ;
1+
13
05
#600
0!
0@
09
b0 O
b1 O
b10 O
b11 O
b100 O
b101 O
#605
1!
1@
19
b0 <
b1 <
b10 <
b11 <
b100 <
b101 <
b10 ;
0+
1*
11
12
03
04
#610
0!
0@
09
1Q
0L
0M
b0 O
b1 O
b10 O
b11 O
b100 O
b101 O
0&
0%
b0 N
#615
1!
1@
19
b0 <
b1 <
b10 <
b11 <
b100 <
b101 <
10
02
#620
0!
0@
09
b0 O
b1 O
b10 O
b11 O
b100 O
b101 O
#625
1!
1@
19
#630
0!
0@
09
b0 O
b1 O
b10 O
b11 O
b100 O
b101 O
#635
1!
1@
19
#640
0!
0@
09
b0 O
b1 O
b10 O
b11 O
b100 O
b101 O
#645
1!
1@
19
#650
0!
0@
09
b0 O
b1 O
b10 O
b11 O
b100 O
b101 O
#655
1!
1@
19
#660
0!
0@
09
b0 O
b1 O
b10 O
b11 O
b100 O
b101 O
#665
1!
1@
19
#670
0!
0@
09
b0 O
b1 O
b10 O
b11 O
b100 O
b101 O
#675
1!
1@
19
#680
0!
0@
09
b0 O
b1 O
b10 O
b11 O
b100 O
b101 O
#685
1!
1@
19
#690
b1000 #
0!
1H
0@
09
b0 O
b1 O
b10 O
b11 O
b100 O
b101 O
b1000 N
#695
1!
1@
19
#700
b0 #
0!
0H
0@
09
b11 P
0Q
b0 O
b1 O
b10 O
b11 O
b100 O
b101 O
1L
1M
1&
1%
#705
1!
1@
19
#710
0!
0@
09
b0 O
b1 O
b10 O
b11 O
b100 O
b101 O
#715
1!
1@
19
b0 <
b1 <
b10 <
b11 <
b100 <
b101 <
b11 ;
1+
1/
01
#720
b10 $
0!
1E
0@
09
1Q
0L
0M
b0 O
b1 O
b10 O
b11 O
b100 O
b101 O
0&
0%
b1010 N
b10 N
#725
1!
1@
19
b0 <
b1 <
b10 <
b11 <
b100 <
b101 <
1.
00
#730
b0 $
0!
0E
0@
09
b1 P
0Q
b0 O
b1 O
b10 O
b11 O
b100 O
b101 O
1M
1%
#735
1!
1@
19
#740
0!
0@
09
b0 O
b1 O
b10 O
b11 O
b100 O
b101 O
#745
1!
1@
19
#750
b10000 $
0!
1B
0@
09
b0 O
b1 O
b10 O
b11 O
b100 O
b101 O
b10010 N
#755
1!
1@
19
#760
b0 $
0!
0B
0@
09
b0 O
b1 O
b10 O
b11 O
b100 O
b101 O
#765
1!
1@
19
#770
0!
0@
09
b0 O
b1 O
b10 O
b11 O
b100 O
b101 O
#775
1!
1@
19
#780
0!
0@
09
b0 O
b1 O
b10 O
b11 O
b100 O
b101 O
#785
1!
1@
19
#790
0!
0@
09
b0 O
b1 O
b10 O
b11 O
b100 O
b101 O
#795
1!
1@
19
#800
0!
0@
09
b0 O
b1 O
b10 O
b11 O
b100 O
b101 O
#805
1!
1@
19
#810
0!
0@
09
b0 O
b1 O
b10 O
b11 O
b100 O
b101 O
#815
1!
1@
19
#820
0!
0@
09
b0 O
b1 O
b10 O
b11 O
b100 O
b101 O
#825
1!
1@
19
b0 <
b1 <
b10 <
b11 <
b100 <
b101 <
b10 ;
0+
0/
11
#830
0!
0@
09
b0 O
b1 O
b10 O
b11 O
b100 O
b101 O
#835
1!
1@
19
b0 <
b1 <
b10 <
b11 <
b100 <
b101 <
b1 ;
1+
0*
0.
10
01
13
#840
0!
0@
09
1Q
0M
b0 O
b1 O
b10 O
b11 O
b100 O
b101 O
0%
b10000 N
#845
1!
1@
19
b0 <
b1 <
b10 <
b11 <
b100 <
b101 <
00
12
#850
0!
0@
09
b100 P
0Q
b0 O
b1 O
b10 O
b11 O
b100 O
b101 O
1L
1M
1&
1%
#855
1!
1@
19
#860
0!
0@
09
b0 O
b1 O
b10 O
b11 O
b100 O
b101 O
#865
1!
1@
19
#870
0!
0@
09
b0 O
b1 O
b10 O
b11 O
b100 O
b101 O
#875
1!
1@
19
#880
0!
0@
09
b0 O
b1 O
b10 O
b11 O
b100 O
b101 O
#885
1!
1@
19
#890
0!
0@
09
b0 O
b1 O
b10 O
b11 O
b100 O
b101 O
#895
1!
1@
19
#900
0!
0@
09
b0 O
b1 O
b10 O
b11 O
b100 O
b101 O
#905
1!
1@
19
#910
0!
0@
09
b0 O
b1 O
b10 O
b11 O
b100 O
b101 O
#915
1!
1@
19
#920
0!
0@
09
b0 O
b1 O
b10 O
b11 O
b100 O
b101 O
#925
1!
1@
19
#930
0!
0@
09
b0 O
b1 O
b10 O
b11 O
b100 O
b101 O
#935
1!
1@
19
#940
0!
0@
09
b0 O
b1 O
b10 O
b11 O
b100 O
b101 O
#945
1!
1@
19
b0 <
b1 <
b10 <
b11 <
b100 <
b101 <
b10 ;
0+
1*
11
03
#950
0!
0@
09
b0 O
b1 O
b10 O
b11 O
b100 O
b101 O
#955
1!
1@
19
b0 <
b1 <
b10 <
b11 <
b100 <
b101 <
b11 ;
1+
1/
10
01
02
#960
0!
0@
09
b0 O
b1 O
b10 O
b11 O
b100 O
b101 O
#965
1!
1@
19
b0 <
b1 <
b10 <
b11 <
b100 <
b101 <
b100 ;
0+
0*
1)
1-
1.
0/
00
#970
0!
0@
09
1Q
0L
0M
b0 O
b1 O
b10 O
b11 O
b100 O
b101 O
0&
0%
b0 N
#975
1!
1@
19
b0 <
b1 <
b10 <
b11 <
b100 <
b101 <
1,
0.
#980
0!
0@
09
b0 O
b1 O
b10 O
b11 O
b100 O
b101 O
#985
1!
1@
19
#990
0!
0@
09
b0 O
b1 O
b10 O
b11 O
b100 O
b101 O
#995
1!
1@
19
#1000
0!
0@
09
b0 O
b1 O
b10 O
b11 O
b100 O
b101 O
#1005
1!
1@
19
#1010
0!
0@
09
b0 O
b1 O
b10 O
b11 O
b100 O
b101 O
#1015
1!
1@
19
#1020
0!
0@
09
b0 O
b1 O
b10 O
b11 O
b100 O
b101 O
#1025
1!
1@
19
#1030
0!
0@
09
b0 O
b1 O
b10 O
b11 O
b100 O
b101 O
#1035
1!
1@
19
#1040
0!
0@
09
b0 O
b1 O
b10 O
b11 O
b100 O
b101 O
#1045
1!
1@
19
#1050
0!
0@
09
b0 O
b1 O
b10 O
b11 O
b100 O
b101 O
#1055
1!
1@
19
#1060
0!
0@
09
b0 O
b1 O
b10 O
b11 O
b100 O
b101 O
#1065
1!
1@
19
#1070
0!
0@
09
b0 O
b1 O
b10 O
b11 O
b100 O
b101 O
#1075
1!
1@
19
b0 <
b1 <
b10 <
b11 <
b100 <
b101 <
#1080
0!
0@
09
b0 O
b1 O
b10 O
b11 O
b100 O
b101 O
#1085
1!
1@
19
#1090
0!
0@
09
b0 O
b1 O
b10 O
b11 O
b100 O
b101 O
#1095
1!
1@
19
#1100
0!
0@
09
b0 O
b1 O
b10 O
b11 O
b100 O
b101 O
#1105
1!
1@
19
#1110
0!
0@
09
b0 O
b1 O
b10 O
b11 O
b100 O
b101 O
#1115
1!
1@
19
#1120
0!
0@
09
b0 O
b1 O
b10 O
b11 O
b100 O
b101 O
#1125
1!
1@
19
#1130
0!
0@
09
b0 O
b1 O
b10 O
b11 O
b100 O
b101 O
#1135
1!
1@
19
#1140
0!
0@
09
b0 O
b1 O
b10 O
b11 O
b100 O
b101 O
#1145
1!
1@
19
#1150
0!
0@
09
b0 O
b1 O
b10 O
b11 O
b100 O
b101 O
#1155
1!
1@
19
#1160
0!
0@
09
b0 O
b1 O
b10 O
b11 O
b100 O
b101 O
#1165
1!
1@
19
#1170
0!
0@
09
b0 O
b1 O
b10 O
b11 O
b100 O
b101 O
#1175
1!
1@
19
b0 <
b1 <
b10 <
b11 <
b100 <
b101 <
#1180
0!
0@
09
b0 O
b1 O
b10 O
b11 O
b100 O
b101 O
#1185
1!
1@
19
#1190
0!
0@
09
b0 O
b1 O
b10 O
b11 O
b100 O
b101 O
#1195
1!
1@
19
#1200
0!
0@
09
b0 O
b1 O
b10 O
b11 O
b100 O
b101 O
#1205
1!
1@
19
#1210
0!
0@
09
b0 O
b1 O
b10 O
b11 O
b100 O
b101 O
#1215
1!
1@
19
#1220
0!
0@
09
b0 O
b1 O
b10 O
b11 O
b100 O
b101 O
#1225
1!
1@
19
#1230
0!
0@
09
b0 O
b1 O
b10 O
b11 O
b100 O
b101 O
#1235
1!
1@
19
#1240
0!
0@
09
b0 O
b1 O
b10 O
b11 O
b100 O
b101 O
#1245
1!
1@
19
#1250
0!
0@
09
b0 O
b1 O
b10 O
b11 O
b100 O
b101 O
#1255
1!
1@
19
#1260
0!
0@
09
b0 O
b1 O
b10 O
b11 O
b100 O
b101 O
#1265
1!
1@
19
#1270
0!
0@
09
b0 O
b1 O
b10 O